[{"Temperature": {"UnitType": 17, "Unit": "C", "Value": 17.2}, "IceProbability": 0, "RealFeelTemperature": {"UnitType": 17, "Unit": "C", "Value": 17.0}, "Ice": {"UnitType": 3, "Unit": "mm", "Value": 0.0}, "DateTime": "2019-03-29T19:00:00+01:00", "WeatherIcon": 1, "Rain": {"UnitType": 3, "Unit": "mm", "Value": 0.0}, "WindGust": {"Speed": {"UnitType": 7, "Unit": "km/h", "Value": 9.3}}, "TotalLiquid": {"UnitType": 3, "Unit": "mm", "Value": 0.0}, "Ceiling": {"UnitType": 5, "Unit": "m", "Value": 8047.0}, "RainProbability": 0, "Visibility": {"UnitType": 6, "Unit": "km", "Value": 16.1}, "EpochDateTime": 1553882400, "Link": "http://www.accuweather.com/es/es/jaen/306731/hourly-weather-forecast/306731?day=1&hbhhour=19&unit=c", "IconPhrase": "Soleado", "RelativeHumidity": 28, "DewPoint": {"UnitType": 17, "Unit": "C", "Value": -1.3}, "CloudCover": 4, "UVIndexText": "Bajo", "Snow": {"UnitType": 4, "Unit": "cm", "Value": 0.0}, "WetBulbTemperature": {"UnitType": 17, "Unit": "C", "Value": 8.5}, "MobileLink": "http://m.accuweather.com/es/es/jaen/306731/hourly-weather-forecast/306731?day=1&unit=c", "Wind": {"Direction": {"Degrees": 60, "Localized": "ENE", "English": "ENE"}, "Speed": {"UnitType": 7, "Unit": "km/h", "Value": 7.4}}, "IsDaylight": true, "SnowProbability": 0, "PrecipitationProbability": 0, "UVIndex": 0}, {"Temperature": {"UnitType": 17, "Unit": "C", "Value": 14.4}, "IceProbability": 0, "RealFeelTemperature": {"UnitType": 17, "Unit": "C", "Value": 14.2}, "Ice": {"UnitType": 3, "Unit": "mm", "Value": 0.0}, "DateTime": "2019-03-29T20:00:00+01:00", "WeatherIcon": 34, "Rain": {"UnitType": 3, "Unit": "mm", "Value": 0.0}, "WindGust": {"Speed": {"UnitType": 7, "Unit": "km/h", "Value": 9.3}}, "TotalLiquid": {"UnitType": 3, "Unit": "mm", "Value": 0.0}, "Ceiling": {"UnitType": 5, "Unit": "m", "Value": 8321.0}, "RainProbability": 0, "Visibility": {"UnitType": 6, "Unit": "km", "Value": 16.1}, "EpochDateTime": 1553886000, "Link": "http://www.accuweather.com/es/es/jaen/306731/hourly-weather-forecast/306731?day=1&hbhhour=20&unit=c", "IconPhrase": "Mayormente despejado", "RelativeHumidity": 37, "DewPoint": {"UnitType": 17, "Unit": "C", "Value": -0.2}, "CloudCover": 14, "UVIndexText": "Bajo", "Snow": {"UnitType": 4, "Unit": "cm", "Value": 0.0}, "WetBulbTemperature": {"UnitType": 17, "Unit": "C", "Value": 7.6}, "MobileLink": "http://m.accuweather.com/es/es/jaen/306731/hourly-weather-forecast/306731?day=1&unit=c", "Wind": {"Direction": {"Degrees": 61, "Localized": "ENE", "English": "ENE"}, "Speed": {"UnitType": 7, "Unit": "km/h", "Value": 7.4}}, "IsDaylight": false, "SnowProbability": 0, "PrecipitationProbability": 0, "UVIndex": 0}, {"Temperature": {"UnitType": 17, "Unit": "C", "Value": 11.9}, "IceProbability": 0, "RealFeelTemperature": {"UnitType": 17, "Unit": "C", "Value": 11.8}, "Ice": {"UnitType": 3, "Unit": "mm", "Value": 0.0}, "DateTime": "2019-03-29T21:00:00+01:00", "WeatherIcon": 34, "Rain": {"UnitType": 3, "Unit": "mm", "Value": 0.0}, "WindGust": {"Speed": {"UnitType": 7, "Unit": "km/h", "Value": 9.3}}, "TotalLiquid": {"UnitType": 3, "Unit": "mm", "Value": 0.0}, "Ceiling": {"UnitType": 5, "Unit": "m", "Value": 9266.0}, "RainProbability": 0, "Visibility": {"UnitType": 6, "Unit": "km", "Value": 16.1}, "EpochDateTime": 1553889600, "Link": "http://www.accuweather.com/es/es/jaen/306731/hourly-weather-forecast/306731?day=1&hbhhour=21&unit=c", "IconPhrase": "Mayormente despejado", "RelativeHumidity": 47, "DewPoint": {"UnitType": 17, "Unit": "C", "Value": 0.8}, "CloudCover": 23, "UVIndexText": "Bajo", "Snow": {"UnitType": 4, "Unit": "cm", "Value": 0.0}, "WetBulbTemperature": {"UnitType": 17, "Unit": "C", "Value": 6.8}, "MobileLink": "http://m.accuweather.com/es/es/jaen/306731/hourly-weather-forecast/306731?day=1&unit=c", "Wind": {"Direction": {"Degrees": 74, "Localized": "ENE", "English": "ENE"}, "Speed": {"UnitType": 7, "Unit": "km/h", "Value": 7.4}}, "IsDaylight": false, "SnowProbability": 0, "PrecipitationProbability": 0, "UVIndex": 0}, {"Temperature": {"UnitType": 17, "Unit": "C", "Value": 9.6}, "IceProbability": 0, "RealFeelTemperature": {"UnitType": 17, "Unit": "C", "Value": 9.5}, "Ice": {"UnitType": 3, "Unit": "mm", "Value": 0.0}, "DateTime": "2019-03-29T22:00:00+01:00", "WeatherIcon": 35, "Rain": {"UnitType": 3, "Unit": "mm", "Value": 0.0}, "WindGust": {"Speed": {"UnitType": 7, "Unit": "km/h", "Value": 9.3}}, "TotalLiquid": {"UnitType": 3, "Unit": "mm", "Value": 0.0}, "Ceiling": {"UnitType": 5, "Unit": "m", "Value": 9754.0}, "RainProbability": 0, "Visibility": {"UnitType": 6, "Unit": "km", "Value": 16.1}, "EpochDateTime": 1553893200, "Link": "http://www.accuweather.com/es/es/jaen/306731/hourly-weather-forecast/306731?day=1&hbhhour=22&unit=c", "IconPhrase": "Parcialmente nublado", "RelativeHumidity": 57, "DewPoint": {"UnitType": 17, "Unit": "C", "Value": 1.5}, "CloudCover": 32, "UVIndexText": "Bajo", "Snow": {"UnitType": 4, "Unit": "cm", "Value": 0.0}, "WetBulbTemperature": {"UnitType": 17, "Unit": "C", "Value": 5.9}, "MobileLink": "http://m.accuweather.com/es/es/jaen/306731/hourly-weather-forecast/306731?day=1&unit=c", "Wind": {"Direction": {"Degrees": 127, "Localized": "SE", "English": "SE"}, "Speed": {"UnitType": 7, "Unit": "km/h", "Value": 7.4}}, "IsDaylight": false, "SnowProbability": 0, "PrecipitationProbability": 0, "UVIndex": 0}, {"Temperature": {"UnitType": 17, "Unit": "C", "Value": 8.6}, "IceProbability": 0, "RealFeelTemperature": {"UnitType": 17, "Unit": "C", "Value": 8.2}, "Ice": {"UnitType": 3, "Unit": "mm", "Value": 0.0}, "DateTime": "2019-03-29T23:00:00+01:00", "WeatherIcon": 34, "Rain": {"UnitType": 3, "Unit": "mm", "Value": 0.0}, "WindGust": {"Speed": {"UnitType": 7, "Unit": "km/h", "Value": 9.3}}, "TotalLiquid": {"UnitType": 3, "Unit": "mm", "Value": 0.0}, "Ceiling": {"UnitType": 5, "Unit": "m", "Value": 9144.0}, "RainProbability": 0, "Visibility": {"UnitType": 6, "Unit": "km", "Value": 16.1}, "EpochDateTime": 1553896800, "Link": "http://www.accuweather.com/es/es/jaen/306731/hourly-weather-forecast/306731?day=1&hbhhour=23&unit=c", "IconPhrase": "Mayormente despejado", "RelativeHumidity": 64, "DewPoint": {"UnitType": 17, "Unit": "C", "Value": 2.1}, "CloudCover": 26, "UVIndexText": "Bajo", "Snow": {"UnitType": 4, "Unit": "cm", "Value": 0.0}, "WetBulbTemperature": {"UnitType": 17, "Unit": "C", "Value": 5.6}, "MobileLink": "http://m.accuweather.com/es/es/jaen/306731/hourly-weather-forecast/306731?day=1&unit=c", "Wind": {"Direction": {"Degrees": 174, "Localized": "S", "English": "S"}, "Speed": {"UnitType": 7, "Unit": "km/h", "Value": 7.4}}, "IsDaylight": false, "SnowProbability": 0, "PrecipitationProbability": 0, "UVIndex": 0}, {"Temperature": {"UnitType": 17, "Unit": "C", "Value": 7.7}, "IceProbability": 0, "RealFeelTemperature": {"UnitType": 17, "Unit": "C", "Value": 7.3}, "Ice": {"UnitType": 3, "Unit": "mm", "Value": 0.0}, "DateTime": "2019-03-30T00:00:00+01:00", "WeatherIcon": 34, "Rain": {"UnitType": 3, "Unit": "mm", "Value": 0.0}, "WindGust": {"Speed": {"UnitType": 7, "Unit": "km/h", "Value": 9.3}}, "TotalLiquid": {"UnitType": 3, "Unit": "mm", "Value": 0.0}, "Ceiling": {"UnitType": 5, "Unit": "m", "Value": 9144.0}, "RainProbability": 0, "Visibility": {"UnitType": 6, "Unit": "km", "Value": 16.1}, "EpochDateTime": 1553900400, "Link": "http://www.accuweather.com/es/es/jaen/306731/hourly-weather-forecast/306731?day=2&hbhhour=0&unit=c", "IconPhrase": "Mayormente despejado", "RelativeHumidity": 68, "DewPoint": {"UnitType": 17, "Unit": "C", "Value": 2.2}, "CloudCover": 21, "UVIndexText": "Bajo", "Snow": {"UnitType": 4, "Unit": "cm", "Value": 0.0}, "WetBulbTemperature": {"UnitType": 17, "Unit": "C", "Value": 5.4}, "MobileLink": "http://m.accuweather.com/es/es/jaen/306731/hourly-weather-forecast/306731?day=2&unit=c", "Wind": {"Direction": {"Degrees": 161, "Localized": "SSE", "English": "SSE"}, "Speed": {"UnitType": 7, "Unit": "km/h", "Value": 7.4}}, "IsDaylight": false, "SnowProbability": 0, "PrecipitationProbability": 0, "UVIndex": 0}, {"Temperature": {"UnitType": 17, "Unit": "C", "Value": 6.9}, "IceProbability": 0, "RealFeelTemperature": {"UnitType": 17, "Unit": "C", "Value": 6.7}, "Ice": {"UnitType": 3, "Unit": "mm", "Value": 0.0}, "DateTime": "2019-03-30T01:00:00+01:00", "WeatherIcon": 34, "Rain": {"UnitType": 3, "Unit": "mm", "Value": 0.0}, "WindGust": {"Speed": {"UnitType": 7, "Unit": "km/h", "Value": 9.3}}, "TotalLiquid": {"UnitType": 3, "Unit": "mm", "Value": 0.0}, "Ceiling": {"UnitType": 5, "Unit": "m", "Value": 9144.0}, "RainProbability": 0, "Visibility": {"UnitType": 6, "Unit": "km", "Value": 16.1}, "EpochDateTime": 1553904000, "Link": "http://www.accuweather.com/es/es/jaen/306731/hourly-weather-forecast/306731?day=2&hbhhour=1&unit=c", "IconPhrase": "Mayormente despejado", "RelativeHumidity": 70, "DewPoint": {"UnitType": 17, "Unit": "C", "Value": 1.8}, "CloudCover": 15, "UVIndexText": "Bajo", "Snow": {"UnitType": 4, "Unit": "cm", "Value": 0.0}, "WetBulbTemperature": {"UnitType": 17, "Unit": "C", "Value": 4.8}, "MobileLink": "http://m.accuweather.com/es/es/jaen/306731/hourly-weather-forecast/306731?day=2&unit=c", "Wind": {"Direction": {"Degrees": 152, "Localized": "SSE", "English": "SSE"}, "Speed": {"UnitType": 7, "Unit": "km/h", "Value": 7.4}}, "IsDaylight": false, "SnowProbability": 0, "PrecipitationProbability": 0, "UVIndex": 0}, {"Temperature": {"UnitType": 17, "Unit": "C", "Value": 6.4}, "IceProbability": 0, "RealFeelTemperature": {"UnitType": 17, "Unit": "C", "Value": 6.3}, "Ice": {"UnitType": 3, "Unit": "mm", "Value": 0.0}, "DateTime": "2019-03-30T02:00:00+01:00", "WeatherIcon": 34, "Rain": {"UnitType": 3, "Unit": "mm", "Value": 0.0}, "WindGust": {"Speed": {"UnitType": 7, "Unit": "km/h", "Value": 9.3}}, "TotalLiquid": {"UnitType": 3, "Unit": "mm", "Value": 0.0}, "Ceiling": {"UnitType": 5, "Unit": "m", "Value": 9144.0}, "RainProbability": 0, "Visibility": {"UnitType": 6, "Unit": "km", "Value": 16.1}, "EpochDateTime": 1553907600, "Link": "http://www.accuweather.com/es/es/jaen/306731/hourly-weather-forecast/306731?day=2&hbhhour=2&unit=c", "IconPhrase": "Mayormente despejado", "RelativeHumidity": 75, "DewPoint": {"UnitType": 17, "Unit": "C", "Value": 2.2}, "CloudCover": 11, "UVIndexText": "Bajo", "Snow": {"UnitType": 4, "Unit": "cm", "Value": 0.0}, "WetBulbTemperature": {"UnitType": 17, "Unit": "C", "Value": 4.7}, "MobileLink": "http://m.accuweather.com/es/es/jaen/306731/hourly-weather-forecast/306731?day=2&unit=c", "Wind": {"Direction": {"Degrees": 146, "Localized": "SE", "English": "SE"}, "Speed": {"UnitType": 7, "Unit": "km/h", "Value": 7.4}}, "IsDaylight": false, "SnowProbability": 0, "PrecipitationProbability": 0, "UVIndex": 0}, {"Temperature": {"UnitType": 17, "Unit": "C", "Value": 5.9}, "IceProbability": 0, "RealFeelTemperature": {"UnitType": 17, "Unit": "C", "Value": 5.9}, "Ice": {"UnitType": 3, "Unit": "mm", "Value": 0.0}, "DateTime": "2019-03-30T03:00:00+01:00", "WeatherIcon": 33, "Rain": {"UnitType": 3, "Unit": "mm", "Value": 0.0}, "WindGust": {"Speed": {"UnitType": 7, "Unit": "km/h", "Value": 9.3}}, "TotalLiquid": {"UnitType": 3, "Unit": "mm", "Value": 0.0}, "Ceiling": {"UnitType": 5, "Unit": "m", "Value": 9144.0}, "RainProbability": 0, "Visibility": {"UnitType": 6, "Unit": "km", "Value": 16.1}, "EpochDateTime": 1553911200, "Link": "http://www.accuweather.com/es/es/jaen/306731/hourly-weather-forecast/306731?day=2&hbhhour=3&unit=c", "IconPhrase": "Despejado", "RelativeHumidity": 62, "DewPoint": {"UnitType": 17, "Unit": "C", "Value": -0.9}, "CloudCover": 7, "UVIndexText": "Bajo", "Snow": {"UnitType": 4, "Unit": "cm", "Value": 0.0}, "WetBulbTemperature": {"UnitType": 17, "Unit": "C", "Value": 3.1}, "MobileLink": "http://m.accuweather.com/es/es/jaen/306731/hourly-weather-forecast/306731?day=2&unit=c", "Wind": {"Direction": {"Degrees": 141, "Localized": "SE", "English": "SE"}, "Speed": {"UnitType": 7, "Unit": "km/h", "Value": 7.4}}, "IsDaylight": false, "SnowProbability": 0, "PrecipitationProbability": 0, "UVIndex": 0}, {"Temperature": {"UnitType": 17, "Unit": "C", "Value": 5.5}, "IceProbability": 0, "RealFeelTemperature": {"UnitType": 17, "Unit": "C", "Value": 5.4}, "Ice": {"UnitType": 3, "Unit": "mm", "Value": 0.0}, "DateTime": "2019-03-30T04:00:00+01:00", "WeatherIcon": 33, "Rain": {"UnitType": 3, "Unit": "mm", "Value": 0.0}, "WindGust": {"Speed": {"UnitType": 7, "Unit": "km/h", "Value": 9.3}}, "TotalLiquid": {"UnitType": 3, "Unit": "mm", "Value": 0.0}, "Ceiling": {"UnitType": 5, "Unit": "m", "Value": 9144.0}, "RainProbability": 0, "Visibility": {"UnitType": 6, "Unit": "km", "Value": 16.1}, "EpochDateTime": 1553914800, "Link": "http://www.accuweather.com/es/es/jaen/306731/hourly-weather-forecast/306731?day=2&hbhhour=4&unit=c", "IconPhrase": "Despejado", "RelativeHumidity": 65, "DewPoint": {"UnitType": 17, "Unit": "C", "Value": -0.6}, "CloudCover": 3, "UVIndexText": "Bajo", "Snow": {"UnitType": 4, "Unit": "cm", "Value": 0.0}, "WetBulbTemperature": {"UnitType": 17, "Unit": "C", "Value": 3.0}, "MobileLink": "http://m.accuweather.com/es/es/jaen/306731/hourly-weather-forecast/306731?day=2&unit=c", "Wind": {"Direction": {"Degrees": 139, "Localized": "SE", "English": "SE"}, "Speed": {"UnitType": 7, "Unit": "km/h", "Value": 7.4}}, "IsDaylight": false, "SnowProbability": 0, "PrecipitationProbability": 0, "UVIndex": 0}, {"Temperature": {"UnitType": 17, "Unit": "C", "Value": 5.1}, "IceProbability": 0, "RealFeelTemperature": {"UnitType": 17, "Unit": "C", "Value": 5.0}, "Ice": {"UnitType": 3, "Unit": "mm", "Value": 0.0}, "DateTime": "2019-03-30T05:00:00+01:00", "WeatherIcon": 33, "Rain": {"UnitType": 3, "Unit": "mm", "Value": 0.0}, "WindGust": {"Speed": {"UnitType": 7, "Unit": "km/h", "Value": 9.3}}, "TotalLiquid": {"UnitType": 3, "Unit": "mm", "Value": 0.0}, "Ceiling": {"UnitType": 5, "Unit": "m", "Value": 9144.0}, "RainProbability": 0, "Visibility": {"UnitType": 6, "Unit": "km", "Value": 16.1}, "EpochDateTime": 1553918400, "Link": "http://www.accuweather.com/es/es/jaen/306731/hourly-weather-forecast/306731?day=2&hbhhour=5&unit=c", "IconPhrase": "Despejado", "RelativeHumidity": 70, "DewPoint": {"UnitType": 17, "Unit": "C", "Value": 0.1}, "CloudCover": 6, "UVIndexText": "Bajo", "Snow": {"UnitType": 4, "Unit": "cm", "Value": 0.0}, "WetBulbTemperature": {"UnitType": 17, "Unit": "C", "Value": 3.2}, "MobileLink": "http://m.accuweather.com/es/es/jaen/306731/hourly-weather-forecast/306731?day=2&unit=c", "Wind": {"Direction": {"Degrees": 143, "Localized": "SE", "English": "SE"}, "Speed": {"UnitType": 7, "Unit": "km/h", "Value": 7.4}}, "IsDaylight": false, "SnowProbability": 0, "PrecipitationProbability": 0, "UVIndex": 0}, {"Temperature": {"UnitType": 17, "Unit": "C", "Value": 4.2}, "IceProbability": 0, "RealFeelTemperature": {"UnitType": 17, "Unit": "C", "Value": 4.2}, "Ice": {"UnitType": 3, "Unit": "mm", "Value": 0.0}, "DateTime": "2019-03-30T06:00:00+01:00", "WeatherIcon": 34, "Rain": {"UnitType": 3, "Unit": "mm", "Value": 0.0}, "WindGust": {"Speed": {"UnitType": 7, "Unit": "km/h", "Value": 9.3}}, "TotalLiquid": {"UnitType": 3, "Unit": "mm", "Value": 0.0}, "Ceiling": {"UnitType": 5, "Unit": "m", "Value": 9144.0}, "RainProbability": 0, "Visibility": {"UnitType": 6, "Unit": "km", "Value": 16.1}, "EpochDateTime": 1553922000, "Link": "http://www.accuweather.com/es/es/jaen/306731/hourly-weather-forecast/306731?day=2&hbhhour=6&unit=c", "IconPhrase": "Mayormente despejado", "RelativeHumidity": 79, "DewPoint": {"UnitType": 17, "Unit": "C", "Value": 0.8}, "CloudCover": 10, "UVIndexText": "Bajo", "Snow": {"UnitType": 4, "Unit": "cm", "Value": 0.0}, "WetBulbTemperature": {"UnitType": 17, "Unit": "C", "Value": 2.9}, "MobileLink": "http://m.accuweather.com/es/es/jaen/306731/hourly-weather-forecast/306731?day=2&unit=c", "Wind": {"Direction": {"Degrees": 150, "Localized": "SSE", "English": "SSE"}, "Speed": {"UnitType": 7, "Unit": "km/h", "Value": 7.4}}, "IsDaylight": false, "SnowProbability": 0, "PrecipitationProbability": 0, "UVIndex": 0}]